pydantic_mongo_orm/__init__.py
pydantic_mongo_orm-0.0.0.dist-info/METADATA
pydantic_mongo_orm-0.0.0.dist-info/WHEEL
pydantic_mongo_orm-0.0.0.dist-info/RECORD
