Metadata-Version: 2.1
Name: pydantic_mongo_orm
Version: 0.0.0
Summary: ORM working with MongoDb and using Pydantic as a model.
Author: Jakub Tesarek
Author-email: jakub@tesarek.me
Requires-Python: >=3.12,<4.0
Classifier: Programming Language :: Python :: 3
Classifier: Programming Language :: Python :: 3.12
Requires-Dist: pydantic (>=2.5.2,<3.0.0)
Requires-Dist: pymongo (>=4.6.1,<5.0.0)
